{
    "title": "Questão 50 - ENEM 2019",
    "index": 50,
    "year": 2019,
    "language": null,
    "discipline": "ciencias-humanas",
    "context": null,
    "files": [],
    "correctAlternative": "C",
    "alternativesIntroduction": "A hospitalidade pura consiste em acolher aquele que chega antes de lhe impor condições, antes de saber e indagar o que quer que seja, ainda que seja um nome ou um “documento” de identidade. Mas ela também supõe que se dirija a ele, de maneira singular, chamando-o portanto e reconhecendo-lhe um nome próprio: “Como você se chama?” A hospitalidade consiste em fazer tudo para se dirigir ao outro, em lhe conceder, até mesmo perguntar seu nome, evitando que essa pergunta se torne uma “condição”, um inquérito policial, um fichamento ou um simples controle das fronteiras. Uma arte e uma poética, mas também toda uma política dependem disso, toda uma ética se decide aí.\nDERRIDA, J. Papel-máquina. São Paulo: Estação Liberdade, 2004 (adaptado).\n \nAssociado ao contexto migratório contemporâneo, o conceito de hospitalidade proposto pelo autor impõe a necessidade de",
    "alternatives": [
        {
            "letter": "A",
            "text": "Anulação da diferença.",
            "file": null,
            "isCorrect": false
        },
        {
            "letter": "B",
            "text": "Cristalização da biografia.",
            "file": null,
            "isCorrect": false
        },
        {
            "letter": "C",
            "text": "Incorporação da alteridade.",
            "file": null,
            "isCorrect": true
        },
        {
            "letter": "D",
            "text": "Supressão da comunicação.",
            "file": null,
            "isCorrect": false
        },
        {
            "letter": "E",
            "text": "Verificação da proveniência.",
            "file": null,
            "isCorrect": false
        }
    ]
}