{
  "year": 2017,
  "title": "Questão 84 da prova azul do primeiro dia do Enem 2017 Segunda Aplicação",
  "index": 84,
  "discipline": "ciencias-humanas",
  "language": null,
  "context": "A conclusão tardia e perversa para o meio ambiente é o verdadeiro desastre ecológico e econômico ocasionado pelo plantio de café em terrenos declivosos. E o mais grave é que tal lavoura continua a ser praticada em moldes não muito diferentes daqueles que arrasaram florestas, solos e águas no século XIX.\n\n                                                  SOFIATTI, A. Destruição e proteção da Mata Atlântica no Rio de Janeiro: ensaio bibliográfico\nacerca da eco-história. História, Ciências, Saúde, n. 2, jul.-out. 1997.",
  "files": [],
  "correctAlternative": "A",
  "alternativesIntroduction": "A atividade agrícola mencionada no texto provocou impactos ambientais ao longo do século XIX porque",
  "alternatives": [
    {
      "letter": "A",
      "text": "reforçava a ocupação extensiva.",
      "file": null,
      "isCorrect": true
    },
    {
      "letter": "B",
      "text": "utilizava o solo do tipo terra roxa.",
      "file": null,
      "isCorrect": false
    },
    {
      "letter": "C",
      "text": "necessitava de recursos hídricos.",
      "file": null,
      "isCorrect": false
    },
    {
      "letter": "D",
      "text": "estimulava investimentos estrangeiros.",
      "file": null,
      "isCorrect": false
    },
    {
      "letter": "E",
      "text": "empregava mão de obra desqualificada.",
      "file": null,
      "isCorrect": false
    }
  ]
}