{
  "year": 2016,
  "title": "Questão 119 - ENEM 2016",
  "index": 119,
  "discipline": "linguagens",
  "language": null,
  "context": "Casamento\n \nHá mulheres que dizem:\nMeu marido, se quiser pescar, pesque,\nmas que limpe os peixes.\nEu não. A qualquer hora da noite me levanto,\najudo a escamar, abrir, retalhar e salgar.\nÉ tão bom, só a gente sozinhos na cozinha,\nde vez em quando os cotovelos se esbarram,\nele fala coisas como “este foi difícil”\n“prateou no ar dando rabanadas”\ne faz o gesto com a mão.\nO silêncio de quando nos vimos a primeira vez\natravessa a cozinha como um rio profundo.\nPor fim, os peixes na travessa,\nvamos dormir.\nCoisas prateadas espocam:\nsomos noivo e noiva.\n\n                                                  PRADO, A. Poesia reunida. São Paulo: Siciliano, 1991.",
  "files": [],
  "correctAlternative": "E",
  "alternativesIntroduction": "O poema de Adélia Prado, que segue a proposta moderna de tematização de fatos cotidianos, apresenta a prosaica ação de limpar peixes na qual a voz lírica reconhece uma",
  "alternatives": [
    {
      "letter": "A",
      "text": "expectativa do marido em relação à esposa.",
      "file": null,
      "isCorrect": false
    },
    {
      "letter": "B",
      "text": "imposição dos afazeres conjugais.",
      "file": null,
      "isCorrect": false
    },
    {
      "letter": "C",
      "text": "disposição para realizar tarefas masculinas.",
      "file": null,
      "isCorrect": false
    },
    {
      "letter": "D",
      "text": "dissonância entre as vozes masculina e feminina.",
      "file": null,
      "isCorrect": false
    },
    {
      "letter": "E",
      "text": "forma de consagração da cumplicidade no casamento.",
      "file": null,
      "isCorrect": true
    }
  ]
}