{
    "title": "Questão 88 - ENEM 2019",
    "index": 88,
    "year": 2019,
    "language": null,
    "discipline": "ciencias-humanas",
    "context": "O bônus demográfico é caracterizado pelo período em que, por causa da redução do número de filhos por mulher, a estrutura populacional fica favorável ao crescimento econômico. Isso acontece porque há proporcionalmente menos crianças na população, e o percentual de idosos ainda não é alto.\n\n**GOIS, A. O Globo, 5 abr. 2015 (adaptado).**",
    "files": [],
    "correctAlternative": "C",
    "alternativesIntroduction": "A ação estatal que contribui para o aproveitamento do bônus demográfico é o estímulo à:",
    "alternatives": [
        {
            "letter": "A",
            "text": "Atração de imigrantes.",
            "file": null,
            "isCorrect": false
        },
        {
            "letter": "B",
            "text": "Elevação da carga tributária.",
            "file": null,
            "isCorrect": false
        },
        {
            "letter": "C",
            "text": "Qualificação da mão de obra.",
            "file": null,
            "isCorrect": true
        },
        {
            "letter": "D",
            "text": "Admissão de exilados políticos.",
            "file": null,
            "isCorrect": false
        },
        {
            "letter": "E",
            "text": "Concessão de aposentadorias.",
            "file": null,
            "isCorrect": false
        }
    ]
}