{
    "title": "Questão 31 - ENEM 2021",
    "index": 31,
    "year": 2021,
    "language": null,
    "discipline": "linguagens",
    "context": "O skate apareceu como forma de vivência no lazer em períodos de baixa nas ondas e ficou conhecido como “surfinho”. No início foram utilizados eixos e rodinhas de patins pregados numa madeira qualquer, para sua composição, sendo as rodas de borracha ou ferro. O grande marco na história do skate ocorreu em 1974, quando o engenheiro químico chamado Frank Nasworthy descobriu o uretano, material mais flexível, que oferecia mais aderência às rodas. A dependência dos skatistas em relação a esse novo material igualmente alavancou o surgimento de novas manobras e possibilitou a um maior número de pessoas inexperientes começar a prática dessa modalidade. O resultado foi a criação de campeonatos, marcas, fábricas e lojas especializadas.\n\nARMBRUST, I; LAURD, G, A, A. O skate e suas possibilidades educacionais. Motriz, jul-set, 2010 (adaptado).",
    "files": [],
    "correctAlternative": "A",
    "alternativesIntroduction": "De acordo com o texto, diversos fatores ao longo do tempo",
    "alternatives": [
        {
            "letter": "A",
            "text": "Contribuíram para a democratização do skate.",
            "file": null,
            "isCorrect": true
        },
        {
            "letter": "B",
            "text": "Evidenciaram as demandas comerciais dos skatistas.",
            "file": null,
            "isCorrect": false
        },
        {
            "letter": "C",
            "text": "Definiram a carreira de skatista profissional.",
            "file": null,
            "isCorrect": false
        },
        {
            "letter": "D",
            "text": "Permitiram que a prática social do skate substituísse o surfe.",
            "file": null,
            "isCorrect": false
        },
        {
            "letter": "E",
            "text": "Indicaram a autonomia dos praticantes de skate.",
            "file": null,
            "isCorrect": false
        }
    ]
}