{
    "title": "Questão 13 - ENEM 2016",
    "index": 13,
    "year": 2016,
    "language": null,
    "discipline": "ciencias-humanas",
    "context": "A Operação Condor está diretamente vinculada às experiências históricas das ditaduras civil-militares que se disseminaram pelo Cone Sul entre as décadas de 1960 e 1980. Depois do Brasil (e do Paraguai de Stroessner), foi a vez da Argentina (1966), Bolívia (1966 e 1971), Uruguai e Chile (1973) e Argentina (novamente, em 1976). Em todos os casos se instalaram ditaduras civil-militares (em menor ou maior medida) com base na Doutrina de Segurança Nacional e tendo como principais características um anticomunismo militante, a identificação do inimigo interno, a imposição do papel político das Forças Armadas e a definição de fronteiras ideológicas.\n\nPADRÓS, E. S. et al. **Ditadura de Segurança Nacional no Rio Grande do Sul (1964-1985)**. história e memória. Porto Alegre: Corag, 2009 (adaptado).",
    "files": [],
    "correctAlternative": "D",
    "alternativesIntroduction": "Levando-se em conta o contexto em que foi criada, a referida operação tinha como objetivo coordenar a",
    "alternatives": [
        {
            "letter": "A",
            "text": "Modificação de limites territoriais.",
            "file": null,
            "isCorrect": false
        },
        {
            "letter": "B",
            "text": "Sobrevivência de oficiais exilados.",
            "file": null,
            "isCorrect": false
        },
        {
            "letter": "C",
            "text": "Interferência de potências mundiais.",
            "file": null,
            "isCorrect": false
        },
        {
            "letter": "D",
            "text": "Repressão de ativistas oposicionistas.",
            "file": null,
            "isCorrect": true
        },
        {
            "letter": "E",
            "text": "Implantação de governos nacionalistas.",
            "file": null,
            "isCorrect": false
        }
    ]
}