{
    "title": "Questão 154 - ENEM 2010",
    "index": 154,
    "year": 2010,
    "language": null,
    "discipline": "matematica",
    "context": "Uma empresa possui um sistema de controle de qualidade que classifica o seu desempenho financeiro anual, tendo como base o do ano anterior. Os conceitos são: insuficiente, quando o crescimento é menor que 1%; regular, quando o crescimento é maior ou igual a 1% e menor que 5%; bom, quando o crescimento é maior ou igual a 5% e menor que 10%; ótimo, quando é maior ou igual a 10% e menor que 20%; e excelente, quando é maior ou igual a 20%. Essa empresa apresentou lucro de R$132000,00 em 2008 e de R$145000,00 em 2009.",
    "files": [],
    "correctAlternative": "C",
    "alternativesIntroduction": "De acordo com esse sistema de controle de qualidade, o desempenho financeiro dessa empresa no ano de 2009 deve ser considerado",
    "alternatives": [
        {
            "letter": "A",
            "text": "Insuficiente.",
            "file": null,
            "isCorrect": false
        },
        {
            "letter": "B",
            "text": "Regular.",
            "file": null,
            "isCorrect": false
        },
        {
            "letter": "C",
            "text": "Bom.",
            "file": null,
            "isCorrect": true
        },
        {
            "letter": "D",
            "text": "Ótimo.",
            "file": null,
            "isCorrect": false
        },
        {
            "letter": "E",
            "text": "Excelente.",
            "file": null,
            "isCorrect": false
        }
    ]
}