{
    "title": "Questão 46 - ENEM 2018",
    "index": 46,
    "year": 2018,
    "language": null,
    "discipline": "ciencias-humanas",
    "context": "No Segundo Congresso internacional de Ciências Geográficas, em 1875, a que compareceram o presidente da República, o governador de Paris e o presidente da Assembleia, o discurso inaugural do almirante La Roucière-Le Noury expôs a atitude predominante no encontro: “Cavalheiros, a Providência nos ditou a obrigação de conhecer e conquistar a terra. Essa ordem suprema é um dos deveres imperiosos inscritos em nossas inteligências e nossas atividades. A geografia, essa ciência que inspira tão bela devoção e em cujo nome foram sacrificadas tantas vítimas, tornou-se a filosofia da terra”.\n\nSAID, E. **Cultura e política**. São Paulo: Cia. das Letras, 1995.",
    "files": [],
    "correctAlternative": "C",
    "alternativesIntroduction": "No contexto histórico apresentado, a exaltação da ciência geográfica decorre do seu uso para o(a)",
    "alternatives": [
        {
            "letter": "A",
            "text": "Preservação cultural dos territórios ocupados.",
            "file": null,
            "isCorrect": false
        },
        {
            "letter": "B",
            "text": "Formação humanitária da sociedade europeia.",
            "file": null,
            "isCorrect": false
        },
        {
            "letter": "C",
            "text": "Catalogação de dados úteis aos propósitos colonialistas.",
            "file": null,
            "isCorrect": true
        },
        {
            "letter": "D",
            "text": "Desenvolvimento de técnicas matemáticas de construção de cartas.",
            "file": null,
            "isCorrect": false
        },
        {
            "letter": "E",
            "text": "Consolidação do conhecimento topográfico como campo acadêmico.",
            "file": null,
            "isCorrect": false
        }
    ]
}